django_google_fonts/__init__.py
django_google_fonts/apps.py
django_google_fonts/tests.py
django_google_fonts/templatetags/__init__.py
django_google_fonts/templatetags/google_fonts.py
django_google_fonts-0.0.3.dist-info/LICENSE.md
django_google_fonts-0.0.3.dist-info/METADATA
django_google_fonts-0.0.3.dist-info/WHEEL
django_google_fonts-0.0.3.dist-info/top_level.txt
django_google_fonts-0.0.3.dist-info/RECORD
