Metadata-Version: 2.1
Name: django-google-fonts
Version: 0.0.3
Summary: Easy to install and offline Google fonts in Django projects
Author-email: Andy McKay <andy@mckay.pub>
Project-URL: Homepage, https://github.com/andymckay/django-google-fonts
Classifier: Programming Language :: Python :: 3
Classifier: License :: OSI Approved :: MIT License
Classifier: Operating System :: OS Independent
Requires-Python: >=3.7
License-File: LICENSE.md
